README.md
setup.py
eprocess/__init__.py
eprocess/decorators.py
eprocess/test_data.py
eprocess/tests.py
eprocess/timer.py
eprocess.egg-info/PKG-INFO
eprocess.egg-info/SOURCES.txt
eprocess.egg-info/dependency_links.txt
eprocess.egg-info/not-zip-safe
eprocess.egg-info/top_level.txt