Metadata-Version: 2.1
Name: eprocess
Version: 1.0
Summary: A lightweight library that help to process, slice and filter a lot of data.
Home-page: https://bitbucket.org/eliosf27/eprocess.git
Author: Elio Rincón
Author-email: eliosf27@gmail.com
License: MIT
Platform: UNKNOWN
Classifier: Programming Language :: Python :: 3
Classifier: License :: OSI Approved :: MIT License
Classifier: Operating System :: OS Independent
